{
    "DNDConfig": null,
    "__parentReadjusting__": false,
    "_height_": {
        "type": "string",
        "value": "10%"
    },
    "_left_": {
        "type": "string",
        "value": "0"
    },
    "_margin_": [
        0,
        0,
        0,
        0
    ],
    "_orientation_": 6,
    "_padding_": [
        0,
        0,
        0,
        0
    ],
    "_percent_": true,
    "_skin_": "s2a10772d98f477e9a51d45beabbe87f",
    "_top_": {
        "type": "number",
        "value": "20"
    },
    "_width_": {
        "type": "string",
        "value": "100%"
    },
    "allboxes": [],
    "autogrowmode": 0,
    "canUpdateUI": true,
    "children": [
        "flxTab1"
    ],
    "clipbounds": true,
    "containerweight": 100,
    "enablescrolling": true,
    "id": "CopyflxTab0c4f3dd7f79e141",
    "info": null,
    "iscustomlayout": false,
    "isvisible": true,
    "kuid": "i2ebb017ca5345d18ff058e461f9d90a",
    "layouttype": 2,
    "name": "kony.ui.FlexContainer",
    "parent": "flxThreeDotsClickContainer",
    "pf": "frmMyJourneys",
    "retaincontentalignment": false,
    "retainflexpositionproperties": false,
    "snapgridsize": 10,
    "snaptogrid": true,
    "wType": "FlexContainer",
    "widgetalignment": 1,
    "zindex": 1
}