{
    "DNDConfig": null,
    "__parentReadjusting__": false,
    "_height_": {
        "type": "string",
        "value": "40%"
    },
    "_margin_": [
        0,
        0,
        0,
        0
    ],
    "_orientation_": 6,
    "_padding_": [
        0,
        0,
        0,
        0
    ],
    "_percent_": true,
    "_skin_": "sd4ee38283574f49839ae7049a4b450c",
    "_width_": {
        "type": "string",
        "value": "9%"
    },
    "allboxes": [],
    "autogrowmode": 0,
    "canUpdateUI": true,
    "centerx": {
        "type": "string",
        "value": "37%"
    },
    "centery": {
        "type": "string",
        "value": "58%"
    },
    "children": [
        "imgArrow1"
    ],
    "clipbounds": true,
    "containerweight": 100,
    "enablescrolling": true,
    "id": "flxImageArrow1",
    "info": null,
    "iscustomlayout": false,
    "isvisible": true,
    "kuid": "ce65e169ccbe4bce9178557d3eb78843",
    "layouttype": 2,
    "name": "kony.ui.FlexContainer",
    "parent": "flexTabs",
    "pf": "frmInspectionExecution",
    "retaincontentalignment": false,
    "retainflexpositionproperties": false,
    "snapgridsize": 10,
    "snaptogrid": true,
    "wType": "FlexContainer",
    "widgetalignment": 1,
    "zindex": 1
}