{
    "DNDConfig": null,
    "__parentReadjusting__": false,
    "_height_": {
        "type": "string",
        "value": "50dp"
    },
    "_margin_": [
        0,
        0,
        0,
        0
    ],
    "_orientation_": 6,
    "_padding_": [
        0,
        0,
        0,
        0
    ],
    "_percent_": true,
    "_skin_": "sd4ee38283574f49839ae7049a4b450c",
    "_top_": {
        "type": "string",
        "value": "10dp"
    },
    "_width_": {
        "type": "string",
        "value": "95%"
    },
    "allboxes": [],
    "autogrowmode": 0,
    "canUpdateUI": true,
    "centerx": {
        "type": "string",
        "value": "50%"
    },
    "children": [
        "CopyLabel0j6f8db5eee374b",
        "CopyFlexContainer0d9c4899314024f"
    ],
    "clipbounds": true,
    "containerweight": 100,
    "enablescrolling": true,
    "id": "CopyflxDate0d00d91eea4ec4e",
    "info": null,
    "iscustomlayout": false,
    "isvisible": true,
    "kuid": "b4ecf5ff24664120a252bd433e9b90ed",
    "layouttype": 2,
    "name": "kony.ui.FlexContainer",
    "parent": "flxScrllLockOut",
    "pf": "frmAddHaspLock",
    "retaincontentalignment": false,
    "retainflexpositionproperties": false,
    "snapgridsize": 10,
    "snaptogrid": true,
    "wType": "FlexContainer",
    "widgetalignment": 1,
    "zindex": 1
}