{
    "DNDConfig": null,
    "__parentReadjusting__": false,
    "_height_": {
        "type": "string",
        "value": "50dp"
    },
    "_left_": {
        "type": "string",
        "value": "0%"
    },
    "_margin_": [
        0,
        0,
        0,
        0
    ],
    "_orientation_": 6,
    "_padding_": [
        0,
        0,
        0,
        0
    ],
    "_percent_": true,
    "_skin_": "sd4ee38283574f49839ae7049a4b450c",
    "_top_": {
        "type": "string",
        "value": "10dp"
    },
    "_width_": {
        "type": "string",
        "value": "100%"
    },
    "allboxes": [],
    "autogrowmode": 0,
    "canUpdateUI": true,
    "children": [
        "imgTool",
        "FlexGroup0g674788630f848"
    ],
    "clipbounds": true,
    "containerweight": 100,
    "enablescrolling": true,
    "id": "flexComponentTool",
    "info": null,
    "iscustomlayout": false,
    "isvisible": true,
    "kuid": "be0622c33d9b4772930b6ac8c9dde7cf",
    "layouttype": 3,
    "name": "kony.ui.FlexContainer",
    "parent": "toolsComponent",
    "pf": "userwidgetmodel",
    "retaincontentalignment": false,
    "retainflexpositionproperties": false,
    "snapgridsize": 10,
    "snaptogrid": true,
    "wType": "FlexContainer",
    "widgetalignment": 1
}