{
    "AS_FlexContainer_a718f051dac64ed98a28ee41ba8078d2": {
        "id": "AS_FlexContainer_a718f051dac64ed98a28ee41ba8078d2",
        "type": "ACTION_SEQUENCE",
        "params": [{
            "datatype": "collection",
            "name": "eventobject"
        }],
        "contextObj": {
            "name": "uwu255d6f2874e4d29bbf4c572e22c5fe7",
            "type": "userwidgets",
            "KUID": "u255d6f2874e4d29bbf4c572e22c5fe7"
        },
        "language": "js",
        "actions": [{
            "id": "ADD_SNIPPET__j8ee24901038404aa658a621078434b2",
            "type": "ADD_SNIPPET",
            "codeSnippet": "this.onForcedCheckin();",
            "parentId": null,
            "callbackType": null
        }]
    }
}