{"DistanceMatrix":{"getDistanceAndTime":{"servicename":"DistanceMatrix","serviceid":"ba807be9-35fb-47d6-8d65-747919326683","type":"integration","operationname":"getDistanceAndTime","operationid":"7617223"}},"fmgKMSService":{"sendPushNotification":{"servicename":"fmgKMSService","serviceid":"72c7de22-e3ba-41d2-b8bd-c2b81dc190da","type":"integration","operationname":"sendPushNotification","operationid":"7617225"}},"fmgPushAccLogin":{"fmgPerformPushLogin":{"servicename":"fmgPushAccLogin","serviceid":"49ff21b3-c9c8-41b6-8f14-95ac3a69a33b","type":"integration","operationname":"fmgPerformPushLogin","operationid":"7617227"}},"GetDataForMessage":{"getMessage":{"servicename":"GetDataForMessage","serviceid":"f1e485b7-7fff-4562-a044-fb8f39ed015c","type":"integration","operationname":"getMessage","operationid":"8082235"},"pushMessage":{"servicename":"GetDataForMessage","serviceid":"f1e485b7-7fff-4562-a044-fb8f39ed015c","type":"integration","operationname":"pushMessage","operationid":"8138906"},"updateStatus":{"servicename":"GetDataForMessage","serviceid":"f1e485b7-7fff-4562-a044-fb8f39ed015c","type":"integration","operationname":"updateStatus","operationid":"8097132"}},"getPushMessageData":{"fetchAllMessages":{"servicename":"getPushMessageData","serviceid":"a5db3cd6-8c02-48d9-997d-787261969627","type":"integration","operationname":"fetchAllMessages","operationid":"8077467"}},"LoginSvc":{"login":{"servicename":"LoginSvc","serviceid":"95b982f2-7bf0-4cd0-b686-af30d4925a11","type":"integration","operationname":"login","operationid":"5990543"}},"PlaceAutocomplete":{"getPlace":{"servicename":"PlaceAutocomplete","serviceid":"b6042453-6b1c-4b61-9ce3-d0910ad37854","type":"integration","operationname":"getPlace","operationid":"6414137"}},"PlaceDetail":{"getDetail":{"servicename":"PlaceDetail","serviceid":"36f5c77d-4fe0-47c8-97ba-cf0ce9a816fe","type":"integration","operationname":"getDetail","operationid":"6414139"}},"placeSearchAutoComplete":{"getPlaceDetails":{"servicename":"placeSearchAutoComplete","serviceid":"1f60b40d-a642-4a04-a60a-978981372303","type":"integration","operationname":"getPlaceDetails","operationid":"7569050"}},"ReverseGeoCode":{"getAddress":{"servicename":"ReverseGeoCode","serviceid":"2dcbe14f-3b0a-42cd-8e88-b36509d049e2","type":"integration","operationname":"getAddress","operationid":"6414141"}},"sampleNTLMSvc":{"getResponse":{"servicename":"sampleNTLMSvc","serviceid":"115fd67f-1ff8-47f2-bc19-e9124d4a1781","type":"integration","operationname":"getResponse","operationid":"8188931"}},"testNtlm":{"getRes":{"servicename":"testNtlm","serviceid":"9f2641aa-0e3f-4b78-a726-79c61100e374","type":"integration","operationname":"getRes","operationid":"8177851"}},"testNTLMSVC":{"getRes":{"servicename":"testNTLMSVC","serviceid":"2be1f89b-2df8-4efc-9763-0ded6ec56dfd","type":"integration","operationname":"getRes","operationid":"8178507"},"getResponse":{"servicename":"testNTLMSVC","serviceid":"2be1f89b-2df8-4efc-9763-0ded6ec56dfd","type":"integration","operationname":"getResponse","operationid":"8193857"},"getResponseFinal":{"servicename":"testNTLMSVC","serviceid":"2be1f89b-2df8-4efc-9763-0ded6ec56dfd","type":"integration","operationname":"getResponseFinal","operationid":"8193860"}},"fmgOrchSvcForPush":{"notifyAdminUsers":{"servicename":"fmgOrchSvcForPush","serviceid":"48872d1e-22df-46d4-9ade-c63e922fdef6","type":"orchestration","operationname":"notifyAdminUsers","operationid":"7617236"}}}