{
    "AS_UWI_fd004361a46346beaa764ea2d1c092ed": {
        "id": "AS_UWI_fd004361a46346beaa764ea2d1c092ed",
        "type": "ACTION_SEQUENCE",
        "params": [{
            "datatype": "collection",
            "name": "eventobject"
        }, {
            "datatype": "string",
            "name": "changedtext"
        }],
        "contextObj": {
            "name": "uwuf6fb999291e4f13944fcfb10b0e781a",
            "type": "userwidgets",
            "KUID": "uf6fb999291e4f13944fcfb10b0e781a"
        },
        "language": "js",
        "actions": [{
            "id": "ADD_SNIPPET__c6482187105b4c7aa0f40808902c9ee9",
            "type": "ADD_SNIPPET",
            "codeSnippet": "this.validateText();",
            "parentId": null,
            "callbackType": null
        }]
    }
}