{
    "@class": "com.kony.gen.viz.model.component.KVizUserWidget",
    "DNDConfig": null,
    "__parentReadjusting__": false,
    "_children_": [],
    "_height_": {
        "type": "string",
        "value": "60dp"
    },
    "_left_": {
        "type": "string",
        "value": "0dp"
    },
    "_margin_": [
        0,
        0,
        0,
        0
    ],
    "_orientation_": 1,
    "_padding_": [
        0,
        0,
        0,
        0
    ],
    "_percent_": true,
    "_skin_": "s92dde69288d4702acea423ac1bb37a4",
    "_top_": {
        "type": "string",
        "value": "0dp"
    },
    "_width_": {
        "type": "string",
        "value": "100%"
    },
    "autogrowmode": 0,
    "canUpdateUI": true,
    "clipbounds": true,
    "containerweight": 0,
    "data": {
        "ide_onClickMenu": "AS_UWI_d349a3483ee14da58275bb1a88d8ede1",
        "isVisibleLabelHeader": true,
        "isVisibleLogo": false,
        "text": "Mechanical Power Press"
    },
    "enablescrolling": true,
    "id": "headerPendingUnlockSummary",
    "info": null,
    "iscustomlayout": false,
    "isvisible": true,
    "kuid": "a43afb6a773b49578e499371022ea8b4",
    "layouttype": 2,
    "masterType": 1,
    "name": "kony.ui.UserWidgetInstance",
    "parent": "frmPendingUnlockSummary",
    "pf": "frmPendingUnlockSummary",
    "retaincontentalignment": false,
    "retainflexpositionproperties": false,
    "snapgridsize": 10,
    "snaptogrid": true,
    "sourceUserWidget": "a9838001d522408fbf85b1ef86206a72",
    "wType": "UserWidgetInstance"
}