{
    "@class": "com.kony.gen.viz.model.component.KVizImage2",
    "DNDConfig": null,
    "__parentReadjusting__": false,
    "_base64_": null,
    "_height_": {
        "type": "string",
        "value": "40%"
    },
    "_left_": {
        "type": "string",
        "value": "0dp"
    },
    "_margin_": [
        0,
        0,
        0,
        0
    ],
    "_padding_": [
        0,
        0,
        0,
        0
    ],
    "_skin_": "s7e06505e00d4b0cb8bc50bb6c16f8b4",
    "_src_": "journeymanagement_edit.png",
    "_top_": {
        "type": "string",
        "value": "0dp"
    },
    "_width_": {
        "type": "string",
        "value": "40%"
    },
    "canUpdateUI": true,
    "centerx": {
        "type": "string",
        "value": "70%"
    },
    "centery": {
        "type": "string",
        "value": "50%"
    },
    "containerweight": 100,
    "context": {
        "channel": "mobile",
        "formID": "MyAccount",
        "platform": "android",
        "templateType": "forms",
        "topLevelBox": null
    },
    "id": "imgRight",
    "imagescalemode": 1,
    "info": null,
    "invokedProperty": "src",
    "iscustomlayout": false,
    "isvisible": true,
    "kuid": "f385b0bbd72048e4a397423c5020dd88",
    "name": "kony.ui.Image2",
    "parent": "flxRight",
    "pf": "MyAccount",
    "retaincontentalignment": false,
    "retainflexpositionproperties": false,
    "srcType": 1,
    "wType": "Image",
    "widgetalignment": 5,
    "zindex": 1
}