{
    "@class": "com.kony.gen.viz.model.component.KVizImage2",
    "DNDConfig": null,
    "__parentReadjusting__": false,
    "_base64_": null,
    "_height_": {
        "type": "string",
        "value": "150dp"
    },
    "_margin_": [
        0,
        0,
        0,
        0
    ],
    "_padding_": [
        0,
        0,
        0,
        0
    ],
    "_right_": {
        "type": "string",
        "value": "5%"
    },
    "_skin_": "s381ecc851804a5f919e298cbd5ab73e",
    "_src_": "clock.png",
    "_width_": {
        "type": "string",
        "value": "150dp"
    },
    "canUpdateUI": true,
    "centery": {
        "type": "number",
        "value": ""
    },
    "containerweight": 100,
    "context": {
        "channel": "desktop",
        "formID": "frmWorkOrderDetails",
        "platform": "desktopweb",
        "templateType": "forms",
        "topLevelBox": null
    },
    "id": "CopyimgEndVA0c496b469eb5a49",
    "imagescalemode": 1,
    "info": null,
    "invokedProperty": "src",
    "iscustomlayout": false,
    "isvisible": true,
    "kuid": "e50c089268e045fcbe099044c439f1da",
    "name": "kony.ui.Image2",
    "parent": "CopyflxEndTimeVA0f6e35b0b5a6743",
    "pf": "frmWorkOrderDetails",
    "responsiveData": {
        "b1": {
            "centerY": {
                "type": "string",
                "value": "50%"
            },
            "height": {
                "type": "string",
                "value": "25dp"
            },
            "src": "clock.png",
            "width": {
                "type": "string",
                "value": "25dp"
            }
        }
    },
    "retaincontentalignment": false,
    "retainflexpositionproperties": false,
    "srcType": 1,
    "wType": "Image",
    "widgetalignment": 5,
    "zindex": 1
}