{
    "@class": "com.kony.gen.viz.model.component.KVizImage2",
    "DNDConfig": null,
    "__parentReadjusting__": false,
    "_base64_": null,
    "_height_": {
        "type": "string",
        "value": "25dp"
    },
    "_left_": {
        "type": "string",
        "value": "0dp"
    },
    "_margin_": [
        0,
        0,
        0,
        0
    ],
    "_padding_": [
        0,
        0,
        0,
        0
    ],
    "_skin_": "s381ecc851804a5f919e298cbd5ab73e",
    "_src_": "checkboxn.png",
    "_top_": {
        "type": "string",
        "value": "0dp"
    },
    "_width_": {
        "type": "string",
        "value": "25dp"
    },
    "canUpdateUI": true,
    "containerweight": 100,
    "context": {
        "channel": "desktop",
        "formID": "frmWorkOrderDetails",
        "platform": "desktopweb",
        "templateType": "forms",
        "topLevelBox": null
    },
    "id": "imgCHeckCompletionSurvey",
    "imagescalemode": 1,
    "info": null,
    "invokedProperty": "src",
    "iscustomlayout": false,
    "isvisible": true,
    "kuid": "dc9ac38d4bb843beb181bdddde920dea",
    "name": "kony.ui.Image2",
    "parent": "flxCheckCompletionSurvey",
    "pf": "frmWorkOrderDetails",
    "responsiveData": {},
    "retaincontentalignment": false,
    "retainflexpositionproperties": false,
    "srcType": 1,
    "wType": "Image",
    "widgetalignment": 5,
    "zindex": 1
}