{
    "DNDConfig": null,
    "__parentReadjusting__": false,
    "_height_": {
        "type": "string",
        "value": "100%"
    },
    "_left_": {
        "type": "string",
        "value": "10%"
    },
    "_margin_": [
        0,
        0,
        0,
        0
    ],
    "_orientation_": 6,
    "_padding_": [
        0,
        0,
        0,
        0
    ],
    "_percent_": true,
    "_skin_": "s4e4e57ce14c4b1db46c627e4679ac33",
    "_top_": {
        "type": "string",
        "value": "0dp"
    },
    "_width_": {
        "type": "string",
        "value": "25%"
    },
    "allboxes": [],
    "autogrowmode": 0,
    "canUpdateUI": true,
    "children": [
        "Image0d42f5ff8b0784c"
    ],
    "clipbounds": true,
    "containerweight": 100,
    "enablescrolling": true,
    "id": "FlexGroup0i17d4cd715c14c",
    "info": null,
    "iscustomlayout": false,
    "isvisible": true,
    "kuid": "f3751f4a79ff4ae4a54042796edeead9",
    "layouttype": 3,
    "name": "kony.ui.FlexContainer",
    "parent": "flxJourney",
    "pf": "frmCopyCopyAsJourney",
    "retaincontentalignment": false,
    "retainflexpositionproperties": false,
    "snapgridsize": 10,
    "snaptogrid": true,
    "wType": "FlexContainer",
    "widgetalignment": 1
}