{
    "classname": "toolsComponent",
    "definitions": {
        "apis": {
            "custom": [],
            "passthrough": []
        },
        "events": {
            "custom": [],
            "passthrough": []
        },
        "groups": {
            "apis": [],
            "events": [],
            "properties": [],
            "widgets": []
        },
        "properties": {
            "custom": [],
            "passthrough": [
                {
                    "access": "Enable",
                    "group": "General",
                    "kuid": "a54682186d8b40a6bf53ed725870d52a",
                    "originalPropertyKey": "src",
                    "propertyIndex": 1,
                    "propertyKey": "srcTool",
                    "pw": {
                        "access": "readwrite",
                        "category": "widget",
                        "dependentKeysKUIDs": null,
                        "displayName": "srcTool",
                        "srcWidget": "imgTool",
                        "type": "string",
                        "uiConfig": {
                            "Button": {
                                "dataRetrieverId": "Imagelist",
                                "dataUpdaterId": "Imagelist",
                                "popupId": "Imagelist",
                                "type": "ImageEditBtn"
                            },
                            "Label": {}
                        },
                        "uiRepresentation": "Label-Label-Button",
                        "wType": "Image"
                    },
                    "srcWgtKUID": "d9acef54dce648cb97836ecac998b983"
                },
                {
                    "access": "Enable",
                    "group": "General",
                    "kuid": "ec85bccf395a409eaf2a9de5feab06c4",
                    "originalPropertyKey": "text",
                    "propertyIndex": 2,
                    "propertyKey": "textToolName",
                    "pw": {
                        "access": "readwrite",
                        "category": "look",
                        "dependentKeysKUIDs": null,
                        "displayName": "textToolName",
                        "srcWidget": "lblToolName",
                        "type": "string",
                        "uiRepresentation": "Label-Textbox",
                        "wType": "Label"
                    },
                    "srcWgtKUID": "b541e9c965034628b86de18774f0552b"
                },
                {
                    "access": "Enable",
                    "group": "General",
                    "kuid": "d645fafa95434838abf834798eaa5b6c",
                    "originalPropertyKey": "text",
                    "propertyIndex": 3,
                    "propertyKey": "textQuantity",
                    "pw": {
                        "access": "readwrite",
                        "category": "look",
                        "dependentKeysKUIDs": null,
                        "displayName": "textQuantity",
                        "srcWidget": "lblQuantity",
                        "type": "string",
                        "uiRepresentation": "Label-Textbox",
                        "wType": "Label"
                    },
                    "srcWgtKUID": "cfe7535cd5d6465e8806d2389d197bad"
                }
            ]
        },
        "widgets": {
            "expose": [],
            "passthrough": []
        }
    },
    "namespace": "com.dfx",
    "version": "1.0.0"
}