{
    "DNDConfig": null,
    "__parentReadjusting__": false,
    "_height_": {
        "type": "string",
        "value": "92%"
    },
    "_left_": {
        "type": "string",
        "value": "0dp"
    },
    "_margin_": [
        0,
        0,
        0,
        0
    ],
    "_orientation_": 6,
    "_padding_": [
        0,
        0,
        0,
        0
    ],
    "_percent_": true,
    "_skin_": "s2e598a055aa44da98c19d3181588cb9",
    "_top_": {
        "type": "string",
        "value": "8%"
    },
    "_width_": {
        "type": "string",
        "value": "100%"
    },
    "allboxes": [],
    "allowhorizontalbounce": false,
    "allowverticalbounce": false,
    "bounces": false,
    "canUpdateUI": true,
    "children": [
        "FlexContainer0b1c68863e9be4e",
        "flxDriverDetailsContainer",
        "flxDetails",
        "flxCarContainer",
        "flxSelectVehicleContainer",
        "CopyflxScrollContainerRequiredCheckList0f9ca074561e640",
        "flxScrollContainerRequiredCheckList"
    ],
    "clipbounds": true,
    "containerweight": 100,
    "decelerat": false,
    "dragg": false,
    "enablescrolling": true,
    "horizontalscrollindicator": true,
    "id": "flxNewJourneyReady",
    "info": null,
    "iscustomlayout": false,
    "isvisible": true,
    "kuid": "h0caf82237394f818dc712391439c00b",
    "layouttype": 4,
    "name": "kony.ui.FlexScrollContainer",
    "pagingenabled": false,
    "parent": "BeginJourney",
    "pf": "BeginJourney",
    "retaincontentalignment": false,
    "retainflexpositionproperties": false,
    "scrolldirection": 2,
    "snapgridsize": 10,
    "snaptogrid": true,
    "track": false,
    "verticalscrollindicator": true,
    "wType": "FlexScrollContainer",
    "widgetalignment": 1,
    "zindex": 1
}