{
    "@class": "com.kony.gen.viz.model.component.KVizLabel",
    "DNDConfig": null,
    "__parentReadjusting__": false,
    "_height_": {
        "type": "string",
        "value": "100%"
    },
    "_margin_": [
        1,
        1,
        1,
        1
    ],
    "_padding_": [
        0,
        0,
        0,
        0
    ],
    "_skin_": "s59f8b9b56f84f47828c7d09537de816",
    "_text_": "Lock Out Asset 5AS745",
    "_width_": {
        "type": "string",
        "value": "100%"
    },
    "_wrapping_": 2,
    "android": {
        "textStyle": {
            "letterSpacing": 0,
            "strikeThrough": false
        }
    },
    "canUpdateUI": true,
    "centerx": {
        "type": "string",
        "value": "50%"
    },
    "centery": {
        "type": "string",
        "value": "50%"
    },
    "containerweight": 100,
    "contentalignment": 5,
    "id": "lblHeader",
    "info": null,
    "ipad": {
        "psp": {
            "wrapping": 2
        }
    },
    "iphone": {
        "psp": {
            "wrapping": 2
        }
    },
    "iscustomlayout": false,
    "isvisible": true,
    "kuid": "e26b07bd86e14106bff61b0959556bab",
    "name": "kony.ui.Label",
    "parent": "flexHeader",
    "pf": "userwidgetmodel",
    "retaincontentalignment": false,
    "retainflexpositionproperties": false,
    "textstyle": {},
    "tooltip": "",
    "wType": "Label",
    "zindex": 1
}